psbbridge/__init__.py
psbbridge/psbbridge.py
psbbridge-0.2.dist-info/METADATA
psbbridge-0.2.dist-info/WHEEL
psbbridge-0.2.dist-info/top_level.txt
psbbridge-0.2.dist-info/RECORD
