Metadata-Version: 2.1
Name: psbbridge
Version: 0.2
Summary: A Bridge for PacSpedd Base with IDE support
Home-page: https://github.com/PacSpedd/psbbridge
Author: PacSpedd
Author-email: pacspedd@outlook.com
License: MIT
Requires-Dist: pacspeddbase
Requires-Dist: maturin
